{"resolveConflictMode":true,"depName2RootPath":{"@types/libSDL2d.so":"D:\\1224\\ohos_sdl2\\ohos-project\\entry\\src\\main\\cpp\\types\\libSDL2d","@ohos/hypium":"D:\\1224\\ohos_sdl2\\ohos-project\\oh_modules\\.ohpm\\@ohos+hypium@1.0.13\\oh_modules\\@ohos\\hypium"},"depName2DepInfo":{"@types/libSDL2d.so":{"dependencyType":"so","isByteCodeHar":false,"pkgRootPath":"D:\\1224\\ohos_sdl2\\ohos-project\\entry\\src\\main\\cpp\\types\\libSDL2d","pkgName":"libSDL2d.so","pkgVersion":""},"@ohos/hypium":{"dependencyType":"other","isByteCodeHar":false,"pkgRootPath":"D:\\1224\\ohos_sdl2\\ohos-project\\oh_modules\\.ohpm\\@ohos+hypium@1.0.13\\oh_modules\\@ohos\\hypium","pkgName":"@ohos/hypium","pkgVersion":"1.0.13"}}}
